milea_notify/__init__.py
milea_notify/admin.py
milea_notify/apps.py
milea_notify/decorators.py
milea_notify/exceptions.py
milea_notify/forms.py
milea_notify/models.py
milea_notify/settings.py
milea_notify/tasks.py
milea_notify/urls.py
milea_notify/utils.py
milea_notify/views.py
milea_notify/locale/de/LC_MESSAGES/django.mo
milea_notify/locale/de/LC_MESSAGES/django.po
milea_notify/migrations/0001_initial.py
milea_notify/migrations/0002_initial.py
milea_notify/migrations/__init__.py
milea_notify/migrations/__pycache__/0001_initial.cpython-311.pyc
milea_notify/migrations/__pycache__/0002_initial.cpython-311.pyc
milea_notify/migrations/__pycache__/__init__.cpython-311.pyc
milea_notify/static/milea_notify/js/header_notifications.js
milea_notify/templates/milea_notify/header_notifications.html
milea_notify/templatetags/milea_notify_tags.py
milea_notify/templatetags/__pycache__/milea_notify_tags.cpython-311.pyc
milea_notify-0.2.2.dist-info/METADATA
milea_notify-0.2.2.dist-info/WHEEL
milea_notify-0.2.2.dist-info/top_level.txt
milea_notify-0.2.2.dist-info/RECORD
